keneth/class_resolver/__init__.py
keneth/class_resolver/class_resolver.py
keneth_class_resolver-0.1.0.dist-info/licenses/LICENSE
keneth_class_resolver-0.1.0.dist-info/METADATA
keneth_class_resolver-0.1.0.dist-info/WHEEL
keneth_class_resolver-0.1.0.dist-info/top_level.txt
keneth_class_resolver-0.1.0.dist-info/RECORD
