Metadata-Version: 2.4
Name: keneth-class-resolver
Version: 0.1.0
Summary: Class Resolver for the Keneth Python web framework.
Author-email: Ismaël Lucas de Leyssac <geodgit@duck.com>
License:                                  Apache License
Project-URL: Homepage, https://github.com/keneth-framework/class-resolver
Requires-Python: >=3.12
License-File: LICENSE
Requires-Dist: keneth-di-contracts>=0.1.0
Dynamic: license-file
